dv_data_engine_client/__init__.py
dv_data_engine_client/api/__init__.py
dv_data_engine_client/api/default/__init__.py
dv_data_engine_client/api/default/append_collaborator.py
dv_data_engine_client/api/default/collaborator_status.py
dv_data_engine_client/api/default/export_collaborator.py
dv_data_engine_client/api/default/mount_collaborator.py
dv_data_engine_client/api/default/query_collaborator.py
dv_data_engine_client/api/default/unmount_collaborator.py
dv_data_engine_client/client.py
dv_data_engine_client/errors.py
dv_data_engine_client/models/__init__.py
dv_data_engine_client/models/append_collaborator_body.py
dv_data_engine_client/models/append_collaborator_response_400.py
dv_data_engine_client/models/append_collaborator_response_404.py
dv_data_engine_client/models/collaborator_status_response_404.py
dv_data_engine_client/models/equal.py
dv_data_engine_client/models/export_collaborator_response_400.py
dv_data_engine_client/models/export_collaborator_response_404.py
dv_data_engine_client/models/expression_type_2.py
dv_data_engine_client/models/expression_type_3.py
dv_data_engine_client/models/greater_than.py
dv_data_engine_client/models/mount_collaborator_body.py
dv_data_engine_client/models/mount_collaborator_body_columns_item.py
dv_data_engine_client/models/mount_collaborator_body_columns_item_type.py
dv_data_engine_client/models/mount_collaborator_response_400.py
dv_data_engine_client/models/mount_collaborator_response_404.py
dv_data_engine_client/models/property_.py
dv_data_engine_client/models/query_collaborator_body.py
dv_data_engine_client/models/query_collaborator_body_join_item.py
dv_data_engine_client/models/query_collaborator_body_select_item.py
dv_data_engine_client/models/query_collaborator_response_400.py
dv_data_engine_client/models/query_collaborator_response_404.py
dv_data_engine_client/models/status_error.py
dv_data_engine_client/models/status_exported.py
dv_data_engine_client/models/status_exported_status.py
dv_data_engine_client-1.0.0.dist-info/METADATA
dv_data_engine_client-1.0.0.dist-info/WHEEL
dv_data_engine_client-1.0.0.dist-info/RECORD
